llm_databricks.py
llm_databricks-0.1.dist-info/LICENSE
llm_databricks-0.1.dist-info/METADATA
llm_databricks-0.1.dist-info/WHEEL
llm_databricks-0.1.dist-info/entry_points.txt
llm_databricks-0.1.dist-info/top_level.txt
llm_databricks-0.1.dist-info/RECORD
